osmosis_ai/__init__.py
osmosis_ai/cli.py
osmosis_ai/cli_commands.py
osmosis_ai/consts.py
osmosis_ai/py.typed
osmosis_ai/rubric_eval.py
osmosis_ai/rubric_types.py
osmosis_ai/utils.py
osmosis_ai/auth/__init__.py
osmosis_ai/auth/config.py
osmosis_ai/auth/credentials.py
osmosis_ai/auth/flow.py
osmosis_ai/auth/local_server.py
osmosis_ai/auth/platform_client.py
osmosis_ai/cli_services/__init__.py
osmosis_ai/cli_services/config.py
osmosis_ai/cli_services/dataset.py
osmosis_ai/cli_services/engine.py
osmosis_ai/cli_services/errors.py
osmosis_ai/cli_services/reporting.py
osmosis_ai/cli_services/session.py
osmosis_ai/cli_services/shared.py
osmosis_ai/providers/__init__.py
osmosis_ai/providers/anthropic_provider.py
osmosis_ai/providers/base.py
osmosis_ai/providers/cerebras_provider.py
osmosis_ai/providers/gemini_provider.py
osmosis_ai/providers/openai_family.py
osmosis_ai/providers/openrouter_provider.py
osmosis_ai/providers/shared.py
osmosis_ai/rollout/__init__.py
osmosis_ai/rollout/_compat.py
osmosis_ai/rollout/cli.py
osmosis_ai/rollout/cli_utils.py
osmosis_ai/rollout/client.py
osmosis_ai/rollout/console.py
osmosis_ai/rollout/network.py
osmosis_ai/rollout/registry.py
osmosis_ai/rollout/testing.py
osmosis_ai/rollout/tools.py
osmosis_ai/rollout/utils.py
osmosis_ai/rollout/validator.py
osmosis_ai/rollout/config/__init__.py
osmosis_ai/rollout/config/settings.py
osmosis_ai/rollout/core/__init__.py
osmosis_ai/rollout/core/base.py
osmosis_ai/rollout/core/exceptions.py
osmosis_ai/rollout/core/llm_client.py
osmosis_ai/rollout/core/schemas.py
osmosis_ai/rollout/server/__init__.py
osmosis_ai/rollout/server/api_key.py
osmosis_ai/rollout/server/app.py
osmosis_ai/rollout/server/registration.py
osmosis_ai/rollout/server/serve.py
osmosis_ai/rollout/server/state.py
osmosis_ai/rollout/test_mode/__init__.py
osmosis_ai/rollout/test_mode/cli.py
osmosis_ai/rollout/test_mode/dataset.py
osmosis_ai/rollout/test_mode/exceptions.py
osmosis_ai/rollout/test_mode/external_llm_client.py
osmosis_ai-0.2.11.dist-info/licenses/LICENSE
osmosis_ai-0.2.11.dist-info/METADATA
osmosis_ai-0.2.11.dist-info/WHEEL
osmosis_ai-0.2.11.dist-info/entry_points.txt
osmosis_ai-0.2.11.dist-info/top_level.txt
osmosis_ai-0.2.11.dist-info/RECORD
