Metadata-Version: 2.4
Name: osmosis-ai
Version: 0.2.11
Summary: A Python SDK for Osmosis LLM training workflows: reward/rubric validation and remote rollout.
Author-email: Osmosis AI <jake@osmosis.ai>
License: MIT License
Project-URL: Homepage, https://github.com/Osmosis-AI/osmosis-sdk-python
Project-URL: Issues, https://github.com/Osmosis-AI/osmosis-sdk-python/issues
Classifier: Programming Language :: Python :: 3
Classifier: License :: OSI Approved :: MIT License
Classifier: Operating System :: OS Independent
Requires-Python: >=3.10
License-File: LICENSE
Requires-Dist: PyYAML<7.0,>=6.0
Requires-Dist: python-dotenv<2.0.0,>=0.1.0
Requires-Dist: requests<3.0.0,>=2.0.0
Requires-Dist: xxhash<4.0.0,>=3.0.0
Requires-Dist: anthropic>=0.72.1
Requires-Dist: openai>=2.0.0
Requires-Dist: google-genai>=1.0.0
Requires-Dist: xai-sdk>=1.2.0
Requires-Dist: cerebras-cloud-sdk>=1.0.0
Requires-Dist: tqdm<5.0.0,>=4.0.0
Requires-Dist: httpx<1.0.0,>=0.25.0
Requires-Dist: pydantic<3.0.0,>=2.0.0
Provides-Extra: server
Requires-Dist: fastapi<1.0.0,>=0.100.0; extra == "server"
Requires-Dist: uvicorn<1.0.0,>=0.23.0; extra == "server"
Requires-Dist: pyarrow>=14.0.0; extra == "server"
Requires-Dist: litellm>=1.40.0; extra == "server"
Requires-Dist: rich>=13.0.0; extra == "server"
Provides-Extra: config
Requires-Dist: pydantic-settings<3.0.0,>=2.0.0; extra == "config"
Provides-Extra: dev
Requires-Dist: pytest<10.0.0,>=8.0.0; extra == "dev"
Requires-Dist: pytest-asyncio<2.0.0,>=0.23.0; extra == "dev"
Requires-Dist: anyio>=4.0.0; extra == "dev"
Requires-Dist: black<26.0.0,>=25.0.0; extra == "dev"
Requires-Dist: isort<7.0.0,>=5.0.0; extra == "dev"
Provides-Extra: full
Requires-Dist: osmosis-ai[config,server]; extra == "full"
Dynamic: license-file
